MANIFEST.in
README.md
requirements.txt
setup.py
docs/source/conf.py
iam.ext.idc.egg-info/PKG-INFO
iam.ext.idc.egg-info/SOURCES.txt
iam.ext.idc.egg-info/dependency_links.txt
iam.ext.idc.egg-info/requires.txt
iam.ext.idc.egg-info/top_level.txt
iam/app/__init__.py
iam/app/asgi.py
iam/app/settings.py
iam/app/urls.py
iam/app/wsgi.py
iam/canon/idc/__init__.py
iam/canon/idc/oauth2credentials.py
iam/canon/idc/oauth2provider.py
iam/canon/idc/oauth2providermetadata.py
iam/canon/idc/oauth2providerspec.py
iam/canon/idc/objectmeta.py
iam/canon/idc/resource.py
iam/ext/idc/VERSION
iam/ext/idc/__init__.py
iam/ext/idc/apps.py
iam/ext/idc/package.json
iam/ext/idc/ctrl/__init__.py
iam/ext/idc/ctrl/authentication.py
iam/ext/idc/ctrl/tests/__init__.py
iam/ext/idc/infra/__init__.py
iam/ext/idc/infra/repo/__init__.py
iam/ext/idc/infra/repo/subject.py
iam/ext/idc/infra/repo/tests/__init__.py
iam/ext/idc/infra/repo/tests/test_system_subjectrepository.py
iam/ext/idc/infra/repo/tests/test_unit_subjectrepository.py
iam/ext/idc/lib/__init__.py
iam/ext/idc/lib/provider.py
iam/ext/idc/lib/registry.py
iam/ext/idc/lib/static.py
iam/ext/idc/lib/loaders/__init__.py
iam/ext/idc/lib/loaders/base.py
iam/ext/idc/lib/loaders/environment.py
iam/ext/idc/lib/loaders/secdir.py
iam/ext/idc/lib/loaders/tests/__init__.py
iam/ext/idc/lib/loaders/tests/test_unit_environment.py
iam/ext/idc/lib/oauth2/__init__.py
iam/ext/idc/lib/oauth2/providers/__init__.py
iam/ext/idc/lib/oauth2/providers/base.py
iam/ext/idc/lib/oauth2/providers/generic.py
iam/ext/idc/lib/oauth2/providers/google.py
iam/ext/idc/lib/oauth2/providers/mock.py
iam/ext/idc/lib/oauth2/providers/oidc.py
iam/ext/idc/lib/oauth2/providers/tests/__init__.py
iam/ext/idc/lib/oauth2/providers/tests/base.py
iam/ext/idc/lib/oauth2/providers/tests/test_oidc.py
iam/ext/idc/lib/oauth2/providers/tests/test_unit_google.py
iam/ext/idc/lib/oauth2/providers/tests/test_unit_oauth.py
iam/ext/idc/lib/tests/__init__.py
iam/ext/idc/migrations/0001_initial.py
iam/ext/idc/migrations/__init__.py
iam/ext/idc/models/__init__.py
iam/ext/idc/models/assertedsubjects.py
iam/ext/idc/tests/__init__.py
iam/ext/idc/tests/test_system_endpoints.py
